{
  "approved_at_utc": null,
  "subreddit": "relationship_advice",
  "selftext": "Sorry, its almost 1am and I'm on my mobile,  so i sacrificed formating. I hope the message still gets across. \n\nSo my friend came to me the other day asking for advice. He said his wife is strongly considering divorce. I said \"what? Why after 23 years?\" He said they took a dna test as part of their family history research and discovered they are 6ths cousins. They share a single common grandparent.\nThis caused his wife to freaked out over the thought that she's had 3 kids with her cousin. When they found out, she ran to the bathroom and started throwing up. Kept screaming how her whole life has been a lie. How she can't understand how she could have been so stupid.  \n\nHe said he's tried many times to talk her out of this. Saying it doesn't matter because they are so far removed, Generally they are not related. He is so regretful that they even took the test and really wished things were back to normal.  However the damage is done, this pandora box is open and it's all she can think about. \n\nHer parents have tried talking with her, her siblings,  friends, coworkers, and all say the same thing, it's not a big deal. But she is focus on how disgusting it is that she has not only slept with her cousin, but she actually married and had kids with him. How she is now just a common idiot hillbilly.\n\n  I said to my friend,  wow, this really sucks but what do you want me to do? What could I possibly say that would help? He asked me what I think he should do and if possible, if I could talk with her. Seems I have always provided solutions to help solve many of their marital problems. He also said she always listens to me. I told him to give me a few days to think about it. This request has been keeping me up for several nights. I don't know what or how to even approach this. So im looking to you.  What can I say?\n\n\nEdit: Corrected some spelling and formatting.\n\nUpdate: So a lot has happened since this post. as I started reading some answers, several mention it may be a mental health issue, so I approached her with that angle. So good and bad news. Since this happened, we were all able to convince her to seek professional help. Her reaction to the DNA results was completely out of character for who she is. our best guess is this was a break down point in her mental state. still unsure what about it put the final stress on her, but in the end, it was the breaking point. \n\nGood news is she sought help. Sad news is she is currently in a mental health center due to underlying mental health issues that had not been diagnosed. No one is clear how she had been able to hide or cope with it all these years. She was diagnosed as bi-polar, schizophrenia, and severe depression. The clinic where she is currently staying is working on a medication balance that will work. As it is right now, she is separated from society until they can get her mental state to a normal level. She is improving, she is allowed visitors and is starting to be more like her self. they have a long road a head of them but I thought I would update everyone here as some of you help me realize there was a lot more to this than just the DNA test. Thanks everyone who posted.",
  "author_fullname": "t2_xavbd",
  "saved": false,
  "mod_reason_title": null,
  "gilded": 0,
  "clicked": false,
  "title": "They're more than kissing cousins.",
  "link_flair_richtext": [],
  "subreddit_name_prefixed": "r/relationship_advice",
  "hidden": false,
  "pwls": 6,
  "link_flair_css_class": null,
  "downs": 0,
  "top_awarded_type": null,
  "hide_score": false,
  "name": "t3_nr5cxw",
  "quarantine": false,
  "link_flair_text_color": "dark",
  "upvote_ratio": 0.96,
  "author_flair_background_color": null,
  "subreddit_type": "public",
  "ups": 830,
  "total_awards_received": 0,
  "media_embed": {},
  "author_flair_template_id": null,
  "is_original_content": false,
  "user_reports": [],
  "secure_media": null,
  "is_reddit_media_domain": false,
  "is_meta": false,
  "category": null,
  "secure_media_embed": {},
  "link_flair_text": null,
  "can_mod_post": false,
  "score": 830,
  "approved_by": null,
  "is_created_from_ads_ui": false,
  "author_premium": false,
  "thumbnail": "",
  "edited": 1626787855.0,
  "author_flair_css_class": null,
  "author_flair_richtext": [],
  "gildings": {},
  "content_categories": null,
  "is_self": true,
  "mod_note": null,
  "created": 1622696448.0,
  "link_flair_type": "text",
  "wls": 6,
  "removed_by_category": null,
  "banned_by": null,
  "author_flair_type": "text",
  "domain": "self.relationship_advice",
  "allow_live_comments": true,
  "selftext_html": "&lt;!-- SC_OFF --&gt;&lt;div class=\"md\"&gt;&lt;p&gt;Sorry, its almost 1am and I&amp;#39;m on my mobile,  so i sacrificed formating. I hope the message still gets across. &lt;/p&gt;\n\n&lt;p&gt;So my friend came to me the other day asking for advice. He said his wife is strongly considering divorce. I said &amp;quot;what? Why after 23 years?&amp;quot; He said they took a dna test as part of their family history research and discovered they are 6ths cousins. They share a single common grandparent.\nThis caused his wife to freaked out over the thought that she&amp;#39;s had 3 kids with her cousin. When they found out, she ran to the bathroom and started throwing up. Kept screaming how her whole life has been a lie. How she can&amp;#39;t understand how she could have been so stupid.  &lt;/p&gt;\n\n&lt;p&gt;He said he&amp;#39;s tried many times to talk her out of this. Saying it doesn&amp;#39;t matter because they are so far removed, Generally they are not related. He is so regretful that they even took the test and really wished things were back to normal.  However the damage is done, this pandora box is open and it&amp;#39;s all she can think about. &lt;/p&gt;\n\n&lt;p&gt;Her parents have tried talking with her, her siblings,  friends, coworkers, and all say the same thing, it&amp;#39;s not a big deal. But she is focus on how disgusting it is that she has not only slept with her cousin, but she actually married and had kids with him. How she is now just a common idiot hillbilly.&lt;/p&gt;\n\n&lt;p&gt;I said to my friend,  wow, this really sucks but what do you want me to do? What could I possibly say that would help? He asked me what I think he should do and if possible, if I could talk with her. Seems I have always provided solutions to help solve many of their marital problems. He also said she always listens to me. I told him to give me a few days to think about it. This request has been keeping me up for several nights. I don&amp;#39;t know what or how to even approach this. So im looking to you.  What can I say?&lt;/p&gt;\n\n&lt;p&gt;Edit: Corrected some spelling and formatting.&lt;/p&gt;\n\n&lt;p&gt;Update: So a lot has happened since this post. as I started reading some answers, several mention it may be a mental health issue, so I approached her with that angle. So good and bad news. Since this happened, we were all able to convince her to seek professional help. Her reaction to the DNA results was completely out of character for who she is. our best guess is this was a break down point in her mental state. still unsure what about it put the final stress on her, but in the end, it was the breaking point. &lt;/p&gt;\n\n&lt;p&gt;Good news is she sought help. Sad news is she is currently in a mental health center due to underlying mental health issues that had not been diagnosed. No one is clear how she had been able to hide or cope with it all these years. She was diagnosed as bi-polar, schizophrenia, and severe depression. The clinic where she is currently staying is working on a medication balance that will work. As it is right now, she is separated from society until they can get her mental state to a normal level. She is improving, she is allowed visitors and is starting to be more like her self. they have a long road a head of them but I thought I would update everyone here as some of you help me realize there was a lot more to this than just the DNA test. Thanks everyone who posted.&lt;/p&gt;\n&lt;/div&gt;&lt;!-- SC_ON --&gt;",
  "likes": null,
  "suggested_sort": null,
  "banned_at_utc": null,
  "view_count": null,
  "archived": true,
  "no_follow": false,
  "is_crosspostable": false,
  "pinned": false,
  "over_18": false,
  "all_awardings": [],
  "awarders": [],
  "media_only": false,
  "can_gild": false,
  "spoiler": false,
  "locked": false,
  "author_flair_text": null,
  "treatment_tags": [],
  "visited": false,
  "removed_by": null,
  "num_reports": null,
  "distinguished": null,
  "subreddit_id": "t5_2r0cn",
  "author_is_blocked": false,
  "mod_reason_by": null,
  "removal_reason": null,
  "link_flair_background_color": "",
  "id": "nr5cxw",
  "is_robot_indexable": true,
  "report_reasons": null,
  "author": "Smoke_Water",
  "discussion_type": null,
  "num_comments": 221,
  "send_replies": true,
  "contest_mode": false,
  "mod_reports": [],
  "author_patreon_flair": false,
  "author_flair_text_color": null,
  "permalink": "/r/relationship_advice/comments/nr5cxw/theyre_more_than_kissing_cousins/",
  "stickied": false,
  "url": "https://www.reddit.com/r/relationship_advice/comments/nr5cxw/theyre_more_than_kissing_cousins/",
  "subreddit_subscribers": 15667768,
  "created_utc": 1622696448.0,
  "num_crossposts": 0,
  "media": null,
  "is_video": false,
  "_search_metadata": {
    "found_via": "keyword_search",
    "keyword_category": "practical_solutions",
    "search_date": "2026-02-24T09:42:05.285249"
  }
}