{
  "approved_at_utc": null,
  "subreddit": "AskWomenOver30",
  "selftext": "I (mid-30s) have two childhood friends I’ve known for about 25 years. We were close growing up, though our connection has been more on-and-off in recent years as we've gone our own ways. Last summer, the three of us planned a trip to visit one of the friends (Friend A) out West. The other friend (Friend B) and I both live in the East, about two hours apart.\n\nFriend B had been going through a rough patch in her relationship and wasn’t sure if she could join the trip. Friend A and I really wanted her to come, so we booked everything in advance and left the door open. Last minute, Friend B said she wanted to come but couldn’t afford the $400CAD for the flight. I found it a little surprising because she's very high income although she had gotten laid off earlier in the year but received a hefty severance and also has other sources of income. Anyhow I offered to cover it, telling her she could pay me back whenever she was able. I really just wanted us all to be together and didn’t want money to be the reason she missed out.\n\nBut then she backed out last minute and didn’t go. She offered to pay me back, but I told her not to worry and just to pay me when she could since she had mentioned earlier that money was a little tight. Fast forward a year,  she never brought it up again, even though we saw each other a few times and reminisced about the trip. It started to feel awkward to me, especially since she never acknowledged that she still owed me.\n\nFinally, after seeing her again recently, I texted her and asked, “Hey, are you able to pay me back for the trip from last year?” She replied, “Oh yeah, I was going to but forgot,” and immediately e-transferred the money. I don't believe she forgot because like I mentioned above, we discussed the trip several times over the year and she agreed she wished she had joined friend B and I. If I were in her place, one conversation on the topic alone would've reminded me I needed to pay back. I've felt resentful that she didn't all this while and I felt awkward asking for it back and I only did because she didn't herself. Part of me can't help but think she was hoping I'd never ask and forget about it.\n\nAnyhow, since our text exchange, I haven’t heard from her, not that we talked regularly, but still I can’t help but wonder if she’s upset I asked for money she owed lol.\n\nFor context, I don’t nickel-and-dime friends, this friend and I often take turns covering food or coffee when we go out, and I would never ask to be paid back for small things. But $400 was a big amount for me, and it felt fair to ask. \n\nDid I handle this wrong? Should I have just let it go?",
  "author_fullname": "t2_46mo9w35",
  "saved": false,
  "mod_reason_title": null,
  "gilded": 0,
  "clicked": false,
  "title": "Was I wrong to ask my friend to pay me back for money owed?",
  "link_flair_richtext": [],
  "subreddit_name_prefixed": "r/AskWomenOver30",
  "hidden": false,
  "pwls": 6,
  "link_flair_css_class": "",
  "downs": 0,
  "thumbnail_height": null,
  "top_awarded_type": null,
  "hide_score": false,
  "name": "t3_1lnvu5e",
  "quarantine": false,
  "link_flair_text_color": "light",
  "upvote_ratio": 0.75,
  "author_flair_background_color": null,
  "subreddit_type": "public",
  "ups": 2,
  "total_awards_received": 0,
  "media_embed": {},
  "thumbnail_width": null,
  "author_flair_template_id": null,
  "is_original_content": false,
  "user_reports": [],
  "secure_media": null,
  "is_reddit_media_domain": false,
  "is_meta": false,
  "category": null,
  "secure_media_embed": {},
  "link_flair_text": "Friendships",
  "can_mod_post": false,
  "score": 2,
  "approved_by": null,
  "is_created_from_ads_ui": false,
  "author_premium": false,
  "thumbnail": "self",
  "edited": 1751250253.0,
  "author_flair_css_class": null,
  "author_flair_richtext": [],
  "gildings": {},
  "content_categories": null,
  "is_self": true,
  "mod_note": null,
  "created": 1751248883.0,
  "link_flair_type": "text",
  "wls": 6,
  "removed_by_category": null,
  "banned_by": null,
  "author_flair_type": "text",
  "domain": "self.AskWomenOver30",
  "allow_live_comments": false,
  "selftext_html": "&lt;!-- SC_OFF --&gt;&lt;div class=\"md\"&gt;&lt;p&gt;I (mid-30s) have two childhood friends I’ve known for about 25 years. We were close growing up, though our connection has been more on-and-off in recent years as we&amp;#39;ve gone our own ways. Last summer, the three of us planned a trip to visit one of the friends (Friend A) out West. The other friend (Friend B) and I both live in the East, about two hours apart.&lt;/p&gt;\n\n&lt;p&gt;Friend B had been going through a rough patch in her relationship and wasn’t sure if she could join the trip. Friend A and I really wanted her to come, so we booked everything in advance and left the door open. Last minute, Friend B said she wanted to come but couldn’t afford the $400CAD for the flight. I found it a little surprising because she&amp;#39;s very high income although she had gotten laid off earlier in the year but received a hefty severance and also has other sources of income. Anyhow I offered to cover it, telling her she could pay me back whenever she was able. I really just wanted us all to be together and didn’t want money to be the reason she missed out.&lt;/p&gt;\n\n&lt;p&gt;But then she backed out last minute and didn’t go. She offered to pay me back, but I told her not to worry and just to pay me when she could since she had mentioned earlier that money was a little tight. Fast forward a year,  she never brought it up again, even though we saw each other a few times and reminisced about the trip. It started to feel awkward to me, especially since she never acknowledged that she still owed me.&lt;/p&gt;\n\n&lt;p&gt;Finally, after seeing her again recently, I texted her and asked, “Hey, are you able to pay me back for the trip from last year?” She replied, “Oh yeah, I was going to but forgot,” and immediately e-transferred the money. I don&amp;#39;t believe she forgot because like I mentioned above, we discussed the trip several times over the year and she agreed she wished she had joined friend B and I. If I were in her place, one conversation on the topic alone would&amp;#39;ve reminded me I needed to pay back. I&amp;#39;ve felt resentful that she didn&amp;#39;t all this while and I felt awkward asking for it back and I only did because she didn&amp;#39;t herself. Part of me can&amp;#39;t help but think she was hoping I&amp;#39;d never ask and forget about it.&lt;/p&gt;\n\n&lt;p&gt;Anyhow, since our text exchange, I haven’t heard from her, not that we talked regularly, but still I can’t help but wonder if she’s upset I asked for money she owed lol.&lt;/p&gt;\n\n&lt;p&gt;For context, I don’t nickel-and-dime friends, this friend and I often take turns covering food or coffee when we go out, and I would never ask to be paid back for small things. But $400 was a big amount for me, and it felt fair to ask. &lt;/p&gt;\n\n&lt;p&gt;Did I handle this wrong? Should I have just let it go?&lt;/p&gt;\n&lt;/div&gt;&lt;!-- SC_ON --&gt;",
  "likes": null,
  "suggested_sort": null,
  "banned_at_utc": null,
  "view_count": null,
  "archived": true,
  "no_follow": false,
  "is_crosspostable": false,
  "pinned": false,
  "over_18": false,
  "all_awardings": [],
  "awarders": [],
  "media_only": false,
  "link_flair_template_id": "05e23960-0b7c-11f0-8ea0-4a6e9b4b9c9f",
  "can_gild": false,
  "spoiler": false,
  "locked": false,
  "author_flair_text": null,
  "treatment_tags": [],
  "visited": false,
  "removed_by": null,
  "num_reports": null,
  "distinguished": null,
  "subreddit_id": "t5_2ya5k",
  "author_is_blocked": false,
  "mod_reason_by": null,
  "removal_reason": null,
  "link_flair_background_color": "#3036cf",
  "id": "1lnvu5e",
  "is_robot_indexable": true,
  "report_reasons": null,
  "author": "desertedstreets",
  "discussion_type": null,
  "num_comments": 7,
  "send_replies": true,
  "contest_mode": false,
  "mod_reports": [],
  "author_patreon_flair": false,
  "author_flair_text_color": null,
  "permalink": "/r/AskWomenOver30/comments/1lnvu5e/was_i_wrong_to_ask_my_friend_to_pay_me_back_for/",
  "stickied": false,
  "url": "https://www.reddit.com/r/AskWomenOver30/comments/1lnvu5e/was_i_wrong_to_ask_my_friend_to_pay_me_back_for/",
  "subreddit_subscribers": 396293,
  "created_utc": 1751248883.0,
  "num_crossposts": 0,
  "media": null,
  "is_video": false,
  "_search_metadata": {
    "found_via": "keyword_search",
    "keyword_category": "success_resolution",
    "search_date": "2026-02-24T10:16:54.617475"
  }
}