{
  "approved_at_utc": null,
  "subreddit": "DeadBedrooms",
  "selftext": "DB started 5 years ago now. 1 year ago I broke down and we had a very serious conversation. We have gone from 4 times a year to at least weekly sometimes more\n\nShe is doing her best to help us as am I   Our intimacy is a lot better than the previous years but it is no where near what it once was\n\nAll this is good news and I think is sustainable long term\n\nMy challenge is my destroyed ego / self esteem. Before the DB I would rate my confidence at 8 out of ten. Three years in I hit a low of maybe 1 out of ten I went into a depression and actually planned suicide wrote her a note and was ready to end it. \n\nFortunately other circumstances delayed things and I woke up and talked with my wife\n\nWith her support I am doing better I feel better but my confidence is 2 or 3 out of ten. I don’t know if I can ever get back to where I once was but I hope I can maybe half way there\n\nMy advice is to not keep your feelings to yourself. Which I did talk with your partner and if they can’t or won’t help you need to do something to change you situation. I let it go too far and did not understand the long term mental damage that was happening to me\n\nI wish everyone here the best and with the wonderful living support of my wife we will continue to do the work needed to move forward \n",
  "author_fullname": "t2_1wy3v2e",
  "saved": false,
  "mod_reason_title": null,
  "gilded": 0,
  "clicked": false,
  "title": "Still working on our DB slow progress after one year",
  "link_flair_richtext": [],
  "subreddit_name_prefixed": "r/DeadBedrooms",
  "hidden": false,
  "pwls": null,
  "link_flair_css_class": null,
  "downs": 0,
  "thumbnail_height": null,
  "top_awarded_type": null,
  "hide_score": false,
  "name": "t3_1ny9o5n",
  "quarantine": false,
  "link_flair_text_color": "dark",
  "upvote_ratio": 0.65,
  "author_flair_background_color": "transparent",
  "subreddit_type": "public",
  "ups": 5,
  "total_awards_received": 0,
  "media_embed": {},
  "thumbnail_width": null,
  "author_flair_template_id": "df91464c-46c3-11f0-9352-722ff543228a",
  "is_original_content": false,
  "user_reports": [],
  "secure_media": null,
  "is_reddit_media_domain": false,
  "is_meta": false,
  "category": null,
  "secure_media_embed": {},
  "link_flair_text": null,
  "can_mod_post": false,
  "score": 5,
  "approved_by": null,
  "is_created_from_ads_ui": false,
  "author_premium": false,
  "thumbnail": "self",
  "edited": false,
  "author_flair_css_class": null,
  "author_flair_richtext": [],
  "gildings": {},
  "content_categories": null,
  "is_self": true,
  "mod_note": null,
  "created": 1759622778.0,
  "link_flair_type": "text",
  "wls": null,
  "removed_by_category": null,
  "banned_by": null,
  "author_flair_type": "text",
  "domain": "self.DeadBedrooms",
  "allow_live_comments": false,
  "selftext_html": "&lt;!-- SC_OFF --&gt;&lt;div class=\"md\"&gt;&lt;p&gt;DB started 5 years ago now. 1 year ago I broke down and we had a very serious conversation. We have gone from 4 times a year to at least weekly sometimes more&lt;/p&gt;\n\n&lt;p&gt;She is doing her best to help us as am I   Our intimacy is a lot better than the previous years but it is no where near what it once was&lt;/p&gt;\n\n&lt;p&gt;All this is good news and I think is sustainable long term&lt;/p&gt;\n\n&lt;p&gt;My challenge is my destroyed ego / self esteem. Before the DB I would rate my confidence at 8 out of ten. Three years in I hit a low of maybe 1 out of ten I went into a depression and actually planned suicide wrote her a note and was ready to end it. &lt;/p&gt;\n\n&lt;p&gt;Fortunately other circumstances delayed things and I woke up and talked with my wife&lt;/p&gt;\n\n&lt;p&gt;With her support I am doing better I feel better but my confidence is 2 or 3 out of ten. I don’t know if I can ever get back to where I once was but I hope I can maybe half way there&lt;/p&gt;\n\n&lt;p&gt;My advice is to not keep your feelings to yourself. Which I did talk with your partner and if they can’t or won’t help you need to do something to change you situation. I let it go too far and did not understand the long term mental damage that was happening to me&lt;/p&gt;\n\n&lt;p&gt;I wish everyone here the best and with the wonderful living support of my wife we will continue to do the work needed to move forward &lt;/p&gt;\n&lt;/div&gt;&lt;!-- SC_ON --&gt;",
  "likes": null,
  "suggested_sort": null,
  "banned_at_utc": null,
  "view_count": null,
  "archived": false,
  "no_follow": false,
  "is_crosspostable": false,
  "pinned": false,
  "over_18": false,
  "all_awardings": [],
  "awarders": [],
  "media_only": false,
  "can_gild": false,
  "spoiler": false,
  "locked": false,
  "author_flair_text": "HLM - Recovered DB",
  "treatment_tags": [],
  "visited": false,
  "removed_by": null,
  "num_reports": null,
  "distinguished": null,
  "subreddit_id": "t5_2t25p",
  "author_is_blocked": false,
  "mod_reason_by": null,
  "removal_reason": null,
  "link_flair_background_color": "",
  "id": "1ny9o5n",
  "is_robot_indexable": true,
  "report_reasons": null,
  "author": "Rick31415926",
  "discussion_type": null,
  "num_comments": 5,
  "send_replies": true,
  "contest_mode": false,
  "mod_reports": [],
  "author_patreon_flair": false,
  "author_flair_text_color": "dark",
  "permalink": "/r/DeadBedrooms/comments/1ny9o5n/still_working_on_our_db_slow_progress_after_one/",
  "stickied": false,
  "url": "https://www.reddit.com/r/DeadBedrooms/comments/1ny9o5n/still_working_on_our_db_slow_progress_after_one/",
  "subreddit_subscribers": 545188,
  "created_utc": 1759622778.0,
  "num_crossposts": 0,
  "media": null,
  "is_video": false,
  "_search_metadata": {
    "found_via": "keyword_search",
    "keyword_category": "success_resolution",
    "search_date": "2026-02-24T10:02:20.101247"
  }
}