{
  "approved_at_utc": null,
  "subreddit": "DeadBedrooms",
  "selftext": "My wife and I have been together for over a decade, we have multiple children and over the past years our sex life really tanked, we both gained weight and poured so much of ourselves into being parents that we kind of forgot how to be lovers, let alone friends.\n\nWe run a nice life and house but my wife hit the gym and made some changes, I followed suit about a year later after she told me she thought our intimacy needed to be addressed in counseling.\n\nI have my own therapist too, I am really trying to do the work. Been eating right, going to doctors, exercising and trying to balance the load of chores and responsibilities.\n\nIts been 4 months but the couples counseling sessions hit hard. There were times where I had anxiety about where we were headed, or times where we weren't clear on each other's visions. We have always been cordial, never attacking.\n\nWe have been trying build intimacy again sometimes it one step forward, one back but it seemed to be trending forward.\n\nBut recently, she has turned ice cold in term of one on one engagement and talking. She isn't mean, at all. She just has nothing to say. She unloaded in counseling that she felt a significant responsibility for making me feel anxiety or that my opinions didn't matter. It hurt to see her like that. Ironically, at the beginning of counseling I felt that way and things have totally flipped.\n\nShe says she isn't attracted to the \"new\" me, even though I have made changes for the better, the changes she specifically asked for.\n\nHearing that hurt, I have never felt so disconnected and incompatible with her.\n\nWe aren't bad people, we never yelled or fought, and maybe that led to use never being honest about how we felt.\n\nIs this part of the healing process? Are just in the middle of an emotional roller coaster that eventually ends well or is it the beginning of the end?\n\nI truly do not know.\n\nI only know this isn't sustainable but it weighs so heavy on her to talk about it. I get that but only discussing it one hour a week at counseling isn't going to be enough.\n\nIf I am too kind, cuddly or vulnerable I am considering needy and using her to emotionally regulate. If I give her space, and don't try to force conversations, it makes her chase me which kind of loops back to me emotionally regulating her.\n\nI am at total loss of what to do.",
  "author_fullname": "t2_1ccnrf1c",
  "saved": false,
  "mod_reason_title": null,
  "gilded": 0,
  "clicked": false,
  "title": "In couples therapy but it seems to be making things heavier and harder",
  "link_flair_richtext": [],
  "subreddit_name_prefixed": "r/DeadBedrooms",
  "hidden": false,
  "pwls": null,
  "link_flair_css_class": "",
  "downs": 0,
  "thumbnail_height": null,
  "top_awarded_type": null,
  "hide_score": false,
  "name": "t3_1r7f92m",
  "quarantine": false,
  "link_flair_text_color": "light",
  "upvote_ratio": 0.88,
  "author_flair_background_color": "transparent",
  "subreddit_type": "public",
  "ups": 28,
  "total_awards_received": 0,
  "media_embed": {},
  "thumbnail_width": null,
  "author_flair_template_id": "e9d6f0a8-4168-11f0-9fd2-b2356e27a078",
  "is_original_content": false,
  "user_reports": [],
  "secure_media": null,
  "is_reddit_media_domain": false,
  "is_meta": false,
  "category": null,
  "secure_media_embed": {},
  "link_flair_text": "Seeking Advice",
  "can_mod_post": false,
  "score": 28,
  "approved_by": null,
  "is_created_from_ads_ui": false,
  "author_premium": false,
  "thumbnail": "self",
  "edited": false,
  "author_flair_css_class": null,
  "author_flair_richtext": [],
  "gildings": {},
  "content_categories": null,
  "is_self": true,
  "mod_note": null,
  "created": 1771354824.0,
  "link_flair_type": "text",
  "wls": null,
  "removed_by_category": null,
  "banned_by": null,
  "author_flair_type": "text",
  "domain": "self.DeadBedrooms",
  "allow_live_comments": false,
  "selftext_html": "&lt;!-- SC_OFF --&gt;&lt;div class=\"md\"&gt;&lt;p&gt;My wife and I have been together for over a decade, we have multiple children and over the past years our sex life really tanked, we both gained weight and poured so much of ourselves into being parents that we kind of forgot how to be lovers, let alone friends.&lt;/p&gt;\n\n&lt;p&gt;We run a nice life and house but my wife hit the gym and made some changes, I followed suit about a year later after she told me she thought our intimacy needed to be addressed in counseling.&lt;/p&gt;\n\n&lt;p&gt;I have my own therapist too, I am really trying to do the work. Been eating right, going to doctors, exercising and trying to balance the load of chores and responsibilities.&lt;/p&gt;\n\n&lt;p&gt;Its been 4 months but the couples counseling sessions hit hard. There were times where I had anxiety about where we were headed, or times where we weren&amp;#39;t clear on each other&amp;#39;s visions. We have always been cordial, never attacking.&lt;/p&gt;\n\n&lt;p&gt;We have been trying build intimacy again sometimes it one step forward, one back but it seemed to be trending forward.&lt;/p&gt;\n\n&lt;p&gt;But recently, she has turned ice cold in term of one on one engagement and talking. She isn&amp;#39;t mean, at all. She just has nothing to say. She unloaded in counseling that she felt a significant responsibility for making me feel anxiety or that my opinions didn&amp;#39;t matter. It hurt to see her like that. Ironically, at the beginning of counseling I felt that way and things have totally flipped.&lt;/p&gt;\n\n&lt;p&gt;She says she isn&amp;#39;t attracted to the &amp;quot;new&amp;quot; me, even though I have made changes for the better, the changes she specifically asked for.&lt;/p&gt;\n\n&lt;p&gt;Hearing that hurt, I have never felt so disconnected and incompatible with her.&lt;/p&gt;\n\n&lt;p&gt;We aren&amp;#39;t bad people, we never yelled or fought, and maybe that led to use never being honest about how we felt.&lt;/p&gt;\n\n&lt;p&gt;Is this part of the healing process? Are just in the middle of an emotional roller coaster that eventually ends well or is it the beginning of the end?&lt;/p&gt;\n\n&lt;p&gt;I truly do not know.&lt;/p&gt;\n\n&lt;p&gt;I only know this isn&amp;#39;t sustainable but it weighs so heavy on her to talk about it. I get that but only discussing it one hour a week at counseling isn&amp;#39;t going to be enough.&lt;/p&gt;\n\n&lt;p&gt;If I am too kind, cuddly or vulnerable I am considering needy and using her to emotionally regulate. If I give her space, and don&amp;#39;t try to force conversations, it makes her chase me which kind of loops back to me emotionally regulating her.&lt;/p&gt;\n\n&lt;p&gt;I am at total loss of what to do.&lt;/p&gt;\n&lt;/div&gt;&lt;!-- SC_ON --&gt;",
  "likes": null,
  "suggested_sort": null,
  "banned_at_utc": null,
  "view_count": null,
  "archived": false,
  "no_follow": false,
  "is_crosspostable": false,
  "pinned": false,
  "over_18": false,
  "all_awardings": [],
  "awarders": [],
  "media_only": false,
  "link_flair_template_id": "015b35e2-5147-11ec-9502-e2e37d398654",
  "can_gild": false,
  "spoiler": false,
  "locked": false,
  "author_flair_text": "I don't wish to disclose",
  "treatment_tags": [],
  "visited": false,
  "removed_by": null,
  "num_reports": null,
  "distinguished": null,
  "subreddit_id": "t5_2t25p",
  "author_is_blocked": false,
  "mod_reason_by": null,
  "removal_reason": null,
  "link_flair_background_color": "#7193ff",
  "id": "1r7f92m",
  "is_robot_indexable": true,
  "report_reasons": null,
  "author": "JamesSDK",
  "discussion_type": null,
  "num_comments": 23,
  "send_replies": true,
  "contest_mode": false,
  "mod_reports": [],
  "author_patreon_flair": false,
  "author_flair_text_color": "dark",
  "permalink": "/r/DeadBedrooms/comments/1r7f92m/in_couples_therapy_but_it_seems_to_be_making/",
  "stickied": false,
  "url": "https://www.reddit.com/r/DeadBedrooms/comments/1r7f92m/in_couples_therapy_but_it_seems_to_be_making/",
  "subreddit_subscribers": 545184,
  "created_utc": 1771354824.0,
  "num_crossposts": 0,
  "media": null,
  "is_video": false
}