{
  "approved_at_utc": null,
  "subreddit": "relationships",
  "selftext": "We both pay for groceries but a lot of the times it doesn't seem fair.  When he has money and he's the one paying for groceries, he complains about the cost, about the frequency. He doesn't do it all of the time but he does it quite often. Asking me to send him back half saying he can't afford it, that most of the food is mine. Other times he will say all of it is mine and ask for the entire amount back. I then send it back to him only for him to end up eating a good amount of the food he said was mine, that he had me pay him back for. A while ago we went on a weekend trip and I covered everything. He didn't have money and I was aware of this. Though he said he would try to give me back some of it (he didn't) When we got back, he got money, and we went to buy groceries. I, without thinking because I'm so accustomed to it, asked if he wanted some back. After I said it, I had hoped he wouldn't and would say no. But he did and then he made his usual remarks that most of the food was mine, that he can't afford it. We got into an argument, I mentioned all I had spent not just on the trip but before. I spent roughly £300 on the trip alone, mostly on food. He said that he didn't make me, that I knew he didn't have money, and that if it had been up to him we wouldn't have gone. I ended up giving him the money back for the groceries. Only for him to several of the items he said were mine, that I had paid him back for.\n\nThis has been going on for some time now. Before, when I've bought things strictly for myself, he would end up eating it and offer to replace it, and most of the time he wouldn't. If I refused to let him eat something, or didn't let him eat as much as he wanted, he would get frustrated with me. Arguing me with one time when he wanted three bags of my popcorn and I told him to take two. Now most of what I buy is for both of us and is meant to be shared. However, before I can get around to having some of it, he will have eaten it having offered none of it to me. With no mention of replacing it or paying me back. He doesn't see it as all that bad. If it's just a few items then it's no big deal. I know, however, if I were to do this with food he bought that he would lose it. Recently he complained after having spent a similar amount to what I did on the trip we went on, about being out of money because of it. I had agreed when he asked to pay him back for a good amount of it. That didn't stop him from going off at me though. Telling me that it was mostly me contributing to the cost, me wanting to go to the store so often, when it was both of us buying food and eating it as usual. He has told me he doesn't need to go, that he could eat what's at the house. Then he goes and buys food anyways and blames me because I took him there. \n\nHe's done this before times we've gone out whether it be to actual food establishments or to a mall. He has bought himself food and then ended up low on money if not out of it. Just to blame me for that saying I took him to the places. If I hadn't of done that, he wouldn't be out of money. We have gone out before and he has expected me to pay, even when he's had money, because it was me who wanted to go. We went to starbucks one time and he asked me to pay for him. Which I normally wouldn't mind doing but leading up to this I was paying for a lot. I then noticed he had money, quite a bit of it, and when I pointed that out he said he wanted to save it. That I should be the one paying for Starbucks because I was the one who wanted to go. We were in America a few years back and were relying on Ubers. We had an agreement to alternate paying, he would pay for one way and I'd pay for the other. I then discovered that he was charging me for both ways and had done so for weeks. I had spent a lot more than I agreed to. When I was angered by this and called him out, he said that it was an accident. But he also said that it was me who had wanted to go the places. The places mostly being grocery stores that we both got food at. But he thought that I should be the one paying. \n\nThere's a lot more than this. Like how he owes me several thousand pounds. Sooner buying things for himself and paying them off or paying his mother back before getting around to me. He says he has to pay her back to remain on good terms because we live with her, because she complains. Times I've mentioned what he owes me, even just the importance of being paid back, he has acted like I'm hassling him when I'm not, when I wait long amounts of time to be paid back in increments. All the while I pay for food for us both and I pay him back frequently for food because he complains, because he says he can't afford it, because he blames me and says it's mine and then he eats it a lot of it anyways. \n\nTDLR - Husband and I both pay for groceries but I don't think it's equal or fair the way he goes about it. Often complaning about how much he's spending, blaming me for it, and asking me for half if not all of what he's spent back, telling me that most of the food bought is mine when it's usually not but even when it has been, he ends up eating the food. Also eating through food I buy for the both of us before I get the chance to have any of it. Having done so before with food I've bought for myself, offering to replace it then rarely doing so. I feel taken advantage of especially because he owes me thousands of pounds. Sooner buying things for himself and paying them off or paying his mother back what he owes her before getting around to me. Yet, here I am paying him back for food he also eats. ",
  "author_fullname": "t2_5py4oh4t",
  "saved": false,
  "mod_reason_title": null,
  "gilded": 0,
  "clicked": false,
  "title": "Husband (27m) eats a lot of the food I buy for us both along with what I (26f) buy for myself or he has me pay him back for ",
  "link_flair_richtext": [],
  "subreddit_name_prefixed": "r/relationships",
  "hidden": false,
  "pwls": 6,
  "link_flair_css_class": null,
  "downs": 0,
  "top_awarded_type": null,
  "hide_score": false,
  "name": "t3_1chghql",
  "quarantine": false,
  "link_flair_text_color": "dark",
  "upvote_ratio": 0.82,
  "author_flair_background_color": null,
  "subreddit_type": "public",
  "ups": 156,
  "total_awards_received": 0,
  "media_embed": {},
  "author_flair_template_id": null,
  "is_original_content": false,
  "user_reports": [],
  "secure_media": null,
  "is_reddit_media_domain": false,
  "is_meta": false,
  "category": null,
  "secure_media_embed": {},
  "link_flair_text": null,
  "can_mod_post": false,
  "score": 156,
  "approved_by": null,
  "is_created_from_ads_ui": false,
  "author_premium": false,
  "thumbnail": "",
  "edited": 1714603459.0,
  "author_flair_css_class": null,
  "author_flair_richtext": [],
  "gildings": {},
  "content_categories": null,
  "is_self": true,
  "mod_note": null,
  "created": 1714549987.0,
  "link_flair_type": "text",
  "wls": 6,
  "removed_by_category": null,
  "banned_by": null,
  "author_flair_type": "text",
  "domain": "self.relationships",
  "allow_live_comments": false,
  "selftext_html": "&lt;!-- SC_OFF --&gt;&lt;div class=\"md\"&gt;&lt;p&gt;We both pay for groceries but a lot of the times it doesn&amp;#39;t seem fair.  When he has money and he&amp;#39;s the one paying for groceries, he complains about the cost, about the frequency. He doesn&amp;#39;t do it all of the time but he does it quite often. Asking me to send him back half saying he can&amp;#39;t afford it, that most of the food is mine. Other times he will say all of it is mine and ask for the entire amount back. I then send it back to him only for him to end up eating a good amount of the food he said was mine, that he had me pay him back for. A while ago we went on a weekend trip and I covered everything. He didn&amp;#39;t have money and I was aware of this. Though he said he would try to give me back some of it (he didn&amp;#39;t) When we got back, he got money, and we went to buy groceries. I, without thinking because I&amp;#39;m so accustomed to it, asked if he wanted some back. After I said it, I had hoped he wouldn&amp;#39;t and would say no. But he did and then he made his usual remarks that most of the food was mine, that he can&amp;#39;t afford it. We got into an argument, I mentioned all I had spent not just on the trip but before. I spent roughly £300 on the trip alone, mostly on food. He said that he didn&amp;#39;t make me, that I knew he didn&amp;#39;t have money, and that if it had been up to him we wouldn&amp;#39;t have gone. I ended up giving him the money back for the groceries. Only for him to several of the items he said were mine, that I had paid him back for.&lt;/p&gt;\n\n&lt;p&gt;This has been going on for some time now. Before, when I&amp;#39;ve bought things strictly for myself, he would end up eating it and offer to replace it, and most of the time he wouldn&amp;#39;t. If I refused to let him eat something, or didn&amp;#39;t let him eat as much as he wanted, he would get frustrated with me. Arguing me with one time when he wanted three bags of my popcorn and I told him to take two. Now most of what I buy is for both of us and is meant to be shared. However, before I can get around to having some of it, he will have eaten it having offered none of it to me. With no mention of replacing it or paying me back. He doesn&amp;#39;t see it as all that bad. If it&amp;#39;s just a few items then it&amp;#39;s no big deal. I know, however, if I were to do this with food he bought that he would lose it. Recently he complained after having spent a similar amount to what I did on the trip we went on, about being out of money because of it. I had agreed when he asked to pay him back for a good amount of it. That didn&amp;#39;t stop him from going off at me though. Telling me that it was mostly me contributing to the cost, me wanting to go to the store so often, when it was both of us buying food and eating it as usual. He has told me he doesn&amp;#39;t need to go, that he could eat what&amp;#39;s at the house. Then he goes and buys food anyways and blames me because I took him there. &lt;/p&gt;\n\n&lt;p&gt;He&amp;#39;s done this before times we&amp;#39;ve gone out whether it be to actual food establishments or to a mall. He has bought himself food and then ended up low on money if not out of it. Just to blame me for that saying I took him to the places. If I hadn&amp;#39;t of done that, he wouldn&amp;#39;t be out of money. We have gone out before and he has expected me to pay, even when he&amp;#39;s had money, because it was me who wanted to go. We went to starbucks one time and he asked me to pay for him. Which I normally wouldn&amp;#39;t mind doing but leading up to this I was paying for a lot. I then noticed he had money, quite a bit of it, and when I pointed that out he said he wanted to save it. That I should be the one paying for Starbucks because I was the one who wanted to go. We were in America a few years back and were relying on Ubers. We had an agreement to alternate paying, he would pay for one way and I&amp;#39;d pay for the other. I then discovered that he was charging me for both ways and had done so for weeks. I had spent a lot more than I agreed to. When I was angered by this and called him out, he said that it was an accident. But he also said that it was me who had wanted to go the places. The places mostly being grocery stores that we both got food at. But he thought that I should be the one paying. &lt;/p&gt;\n\n&lt;p&gt;There&amp;#39;s a lot more than this. Like how he owes me several thousand pounds. Sooner buying things for himself and paying them off or paying his mother back before getting around to me. He says he has to pay her back to remain on good terms because we live with her, because she complains. Times I&amp;#39;ve mentioned what he owes me, even just the importance of being paid back, he has acted like I&amp;#39;m hassling him when I&amp;#39;m not, when I wait long amounts of time to be paid back in increments. All the while I pay for food for us both and I pay him back frequently for food because he complains, because he says he can&amp;#39;t afford it, because he blames me and says it&amp;#39;s mine and then he eats it a lot of it anyways. &lt;/p&gt;\n\n&lt;p&gt;TDLR - Husband and I both pay for groceries but I don&amp;#39;t think it&amp;#39;s equal or fair the way he goes about it. Often complaning about how much he&amp;#39;s spending, blaming me for it, and asking me for half if not all of what he&amp;#39;s spent back, telling me that most of the food bought is mine when it&amp;#39;s usually not but even when it has been, he ends up eating the food. Also eating through food I buy for the both of us before I get the chance to have any of it. Having done so before with food I&amp;#39;ve bought for myself, offering to replace it then rarely doing so. I feel taken advantage of especially because he owes me thousands of pounds. Sooner buying things for himself and paying them off or paying his mother back what he owes her before getting around to me. Yet, here I am paying him back for food he also eats. &lt;/p&gt;\n&lt;/div&gt;&lt;!-- SC_ON --&gt;",
  "likes": null,
  "suggested_sort": "confidence",
  "banned_at_utc": null,
  "view_count": null,
  "archived": true,
  "no_follow": false,
  "is_crosspostable": false,
  "pinned": false,
  "over_18": false,
  "all_awardings": [],
  "awarders": [],
  "media_only": false,
  "can_gild": false,
  "spoiler": false,
  "locked": false,
  "author_flair_text": null,
  "treatment_tags": [],
  "visited": false,
  "removed_by": null,
  "num_reports": null,
  "distinguished": null,
  "subreddit_id": "t5_2qjvn",
  "author_is_blocked": false,
  "mod_reason_by": null,
  "removal_reason": null,
  "link_flair_background_color": "",
  "id": "1chghql",
  "is_robot_indexable": true,
  "report_reasons": null,
  "author": "Clori26",
  "discussion_type": null,
  "num_comments": 306,
  "send_replies": true,
  "contest_mode": false,
  "mod_reports": [],
  "author_patreon_flair": false,
  "author_flair_text_color": null,
  "permalink": "/r/relationships/comments/1chghql/husband_27m_eats_a_lot_of_the_food_i_buy_for_us/",
  "stickied": false,
  "url": "https://www.reddit.com/r/relationships/comments/1chghql/husband_27m_eats_a_lot_of_the_food_i_buy_for_us/",
  "subreddit_subscribers": 3665800,
  "created_utc": 1714549987.0,
  "num_crossposts": 0,
  "media": null,
  "is_video": false,
  "_search_metadata": {
    "found_via": "keyword_search",
    "keyword_category": "practical_solutions",
    "search_date": "2026-02-24T09:52:52.102144"
  }
}